baselmini/__init__.py
baselmini/__main__.py
baselmini/calc.py
baselmini/cli.py
baselmini/config.py
baselmini/exposures.py
baselmini/fx.py
baselmini/io_utils.py
baselmini/ratings.py
baselmini/report.py
baselmini/scenario.py
baselmini/schemas.py
baselmini/validators.py
baselmini-1.0.1.data/data/baselmini_examples/configs/std_approach.yml
baselmini-1.0.1.data/data/baselmini_examples/data/capital.csv
baselmini-1.0.1.data/data/baselmini_examples/data/exposures.csv
baselmini-1.0.1.data/data/baselmini_examples/data/fx.csv
baselmini-1.0.1.data/data/baselmini_examples/data/liquidity.csv
baselmini-1.0.1.data/data/baselmini_examples/data/nsfr.csv
baselmini-1.0.1.data/data/baselmini_examples/golden/expected/results.json
baselmini-1.0.1.data/data/baselmini_examples/golden/inputs/capital.csv
baselmini-1.0.1.data/data/baselmini_examples/golden/inputs/config.yml
baselmini-1.0.1.data/data/baselmini_examples/golden/inputs/exposures.csv
baselmini-1.0.1.data/data/baselmini_examples/golden/inputs/liquidity.csv
baselmini-1.0.1.data/data/baselmini_examples/golden/inputs/nsfr.csv
baselmini-1.0.1.data/data/baselmini_examples/scenarios/ead10_notch1.yml
baselmini-1.0.1.data/data/baselmini_examples/scenarios/shock_fx_10pct.yml
baselmini-1.0.1.dist-info/licenses/LICENSE
baselmini-1.0.1.dist-info/METADATA
baselmini-1.0.1.dist-info/WHEEL
baselmini-1.0.1.dist-info/entry_points.txt
baselmini-1.0.1.dist-info/top_level.txt
baselmini-1.0.1.dist-info/RECORD
