Metadata-Version: 2.4
Name: baselmini
Version: 1.0.1
Summary: Basel III mini engine (credit + liquidity)
Author-email: Edvinas Butkus <ebdev25@gmail.com>
License-Expression: MIT
Project-URL: Homepage, https://github.com/ebdev25
Project-URL: Repository, https://github.com/ebdev25/baselmini
Project-URL: Issues, https://github.com/ebdev25/baselmini/issues
Classifier: Development Status :: 5 - Production/Stable
Classifier: Intended Audience :: Financial and Insurance Industry
Classifier: Programming Language :: Python :: 3
Classifier: Programming Language :: Python :: 3.9
Classifier: Programming Language :: Python :: 3.10
Classifier: Programming Language :: Python :: 3.11
Classifier: Programming Language :: Python :: 3.12
Classifier: Programming Language :: Python :: 3 :: Only
Classifier: Operating System :: OS Independent
Classifier: Topic :: Office/Business :: Financial :: Accounting
Classifier: Topic :: Scientific/Engineering :: Information Analysis
Requires-Python: >=3.9
License-File: LICENSE
Requires-Dist: PyYAML>=6.0
Requires-Dist: tomli; python_version < "3.11"
Dynamic: license-file
